Workbook

Sheet CorST
A1: Слово | B1: Частота-CorST | C1: IPM-CorST | D1: Ранг-CorST | E1: Номер строки, на которой слово стоит в RLC | F1: IPM-RLC
A2: в | B2: 35889 | C2: 11520.564 | E2: =MATCH(A2, RLC!A:A, 0) -> 3 | F2: {=INDEX(RLC!B:B, E2)} -> 28595
A3: и | B3: 31435 | C3: 10090.806 | E3: =MATCH(A3, RLC!A:A, 0) -> 2 | F3: {=INDEX(RLC!B:B, E3)} -> 28852
A4: на | B4: 13212 | C4: 4241.1239 | E4: =MATCH(A4, RLC!A:A, 0) -> 5 | F4: {=INDEX(RLC!B:B, E4)} -> 9984
A5: не | B5: 11811 | C5: 3791.3953 | E5: =MATCH(A5, RLC!A:A, 0) -> 6 | F5: {=INDEX(RLC!B:B, E5)} -> 9679
A6: с | B6: 11363 | C6: 3647.5848 | E6: =MATCH(A6, RLC!A:A, 0) -> 8 | F6: {=INDEX(RLC!B:B, E6)} -> 6908
A7: что | B7: 10265 | C7: 3295.1208 | E7: =MATCH(A7, RLC!A:A, 0) -> 4 | F7: {=INDEX(RLC!B:B, E7)} -> 12272
A8: как | B8: 7396 | C8: 2374.1562 | E8: =MATCH(A8, RLC!A:A, 0) -> 9 | F8: {=INDEX(RLC!B:B, E8)} -> 6227
A9: к | B9: 6790 | C9: 2179.6269 | E9: =MATCH(A9, RLC!A:A, 0) -> 15 | F9: {=INDEX(RLC!B:B, E9)} -> 3569
A10: а | B10: 5924 | C10: 1901.6362 | E10: =MATCH(A10, RLC!A:A, 0) -> 20 | F10: {=INDEX(RLC!B:B, E10)} -> 2596
A11: для | B11: 5652 | C11: 1814.3227 | E11: =MATCH(A11, RLC!A:A, 0) -> 14 | F11: {=INDEX(RLC!B:B, E11)} -> 3770
A12: по | B12: 5634 | C12: 1808.5447 | E12: =MATCH(A12, RLC!A:A, 0) -> 16 | F12: {=INDEX(RLC!B:B, E12)} -> 3493
A13: о | B13: 4912 | C13: 1576.7787 | E13: =MATCH(A13, RLC!A:A, 0) -> 13 | F13: {=INDEX(RLC!B:B, E13)} -> 3780
... A1349: форм | B1349: 92 | C1349: 29.532501 | E1349: =MATCH(A1349, RLC!A:A, 0) -> 5289 | F1349: {=INDEX(RLC!B:B, E1349)} -> 16
A1350: школе | B1350: 92 | C1350: 29.532501 | E1350: =MATCH(A1350, RLC!A:A, 0) -> 404 | F1350: {=INDEX(RLC!B:B, E1350)} -> 195 | G1350: =C1350>E1350 -> FALSE
A1351: элементов | B1351: 92 | C1351: 29.532501 | E1351: =MATCH(A1351, RLC!A:A, 0) -> 4112 | F1351: {=INDEX(RLC!B:B, E1351)} -> 21
A1352: этими | B1352: 92 | C1352: 29.532501 | E1352: =MATCH(A1352, RLC!A:A, 0) -> 1492 | F1352: {=INDEX(RLC!B:B, E1352)} -> 58
A1353: артикля | B1353: 91 | C1353: 29.211495 | E1353: =MATCH(A1353, RLC!A:A, 0) -> #N/A | F1353: {=INDEX(RLC!B:B, E1353)} -> #N/A
A1354: всему | B1354: 91 | C1354: 29.211495 | E1354: =MATCH(A1354, RLC!A:A, 0) -> 741 | F1354: {=INDEX(RLC!B:B, E1354)} -> 109
A1355: выполнения | B1355: 91 | C1355: 29.211495 | E1355: =MATCH(A1355, RLC!A:A, 0) -> #N/A | F1355: {=INDEX(RLC!B:B, E1355)} -> #N/A
A1356: достоевский | B1356: 91 | C1356: 29.211495 | E1356: =MATCH(A1356, RLC!A:A, 0) -> #N/A | F1356: {=INDEX(RLC!B:B, E1356)} -> #N/A
A1357: менеджмента | B1357: 91 | C1357: 29.211495 | E1357: =MATCH(A1357, RLC!A:A, 0) -> 2858 | F1357: {=INDEX(RLC!B:B, E1357)} -> 30
A1358: наша | B1358: 91 | C1358: 29.211495 | E1358: =MATCH(A1358, RLC!A:A, 0) -> 551 | F1358: {=INDEX(RLC!B:B, E1358)} -> 146
A1359: поднятая | B1359: 91 | C1359: 29.211495 | E1359: =MATCH(A1359, RLC!A:A, 0) -> #N/A | F1359: {=INDEX(RLC!B:B, E1359)} -> #N/A
A1360: постепенно | B1360: 91 | C1360: 29.211495 | E1360: =MATCH(A1360, RLC!A:A, 0) -> 2469 | F1360: {=INDEX(RLC!B:B, E1360)} -> 35
A1361: рублей | B1361: 91 | C1361: 29.211495 | E1361: =MATCH(A1361, RLC!A:A, 0) -> 1697 | F1361: {=INDEX(RLC!B:B, E1361)} -> 51
A1362: сегодняшний | B1362: 91 | C1362: 29.211495 | E1362: =MATCH(A1362, RLC!A:A, 0) -> 1873 | F1362: {=INDEX(RLC!B:B, E1362)} -> 47
... A1716: чехов | B1716: 73 | C1716: 23.433397 | E1716: =MATCH(A1716, RLC!A:A, 0) -> #N/A | F1716: {=INDEX(RLC!B:B, E1716)} -> #N/A
A1717: шапочка | B1717: 73 | C1717: 23.433397 | E1717: =MATCH(A1717, RLC!A:A, 0) -> 3340 | F1717: {=INDEX(RLC!B:B, E1717)} -> 26 | G1717: =C1717>E1717 -> FALSE
A1718: широко | B1718: 73 | C1718: 23.433397 | E1718: =MATCH(A1718, RLC!A:A, 0) -> 1585 | F1718: {=INDEX(RLC!B:B, E1718)} -> 55 | G1718: =C1718>E1718 -> FALSE
A1719: эмоций | B1719: 73 | C1719: 23.433397 | E1719: =MATCH(A1719, RLC!A:A, 0) -> 6913 | F1719: {=INDEX(RLC!B:B, E1719)} -> 12
A1720: большие | B1720: 72 | C1720: 23.112392 | E1720: =MATCH(A1720, RLC!A:A, 0) -> 837 | F1720: {=INDEX(RLC!B:B, E1720)} -> 97
A1721: большого | B1721: 72 | C1721: 23.112392 | E1721: =MATCH(A1721, RLC!A:A, 0) -> 2651 | F1721: {=INDEX(RLC!B:B, E1721)} -> 32
A1722: ведет | B1722: 72 | C1722: 23.112392 | E1722: =MATCH(A1722, RLC!A:A, 0) -> 3483 | F1722: {=INDEX(RLC!B:B, E1722)} -> 24
A1723: вниз | B1723: 72 | C1723: 23.112392 | E1723: =MATCH(A1723, RLC!A:A, 0) -> 2832 | F1723: {=INDEX(RLC!B:B, E1723)} -> 30
A1724: вузов | B1724: 72 | C1724: 23.112392 | E1724: =MATCH(A1724, RLC!A:A, 0) -> 6052 | F1724: {=INDEX(RLC!B:B, E1724)} -> 13
A1725: выражений | B1725: 72 | C1725: 23.112392 | E1725: =MATCH(A1725, RLC!A:A, 0) -> 3786 | F1725: {=INDEX(RLC!B:B, E1725)} -> 22
A1726: гражданским | B1726: 72 | C1726: 23.112392 | E1726: =MATCH(A1726, RLC!A:A, 0) -> #N/A | F1726: {=INDEX(RLC!B:B, E1726)} -> #N/A
A1727: изучить | B1727: 72 | C1727: 23.112392 | E1727: =MATCH(A1727, RLC!A:A, 0) -> 4372 | F1727: {=INDEX(RLC!B:B, E1727)} -> 19
A1728: ин | B1728: 72 | C1728: 23.112392 | E1728: =MATCH(A1728, RLC!A:A, 0) -> #N/A | F1728: {=INDEX(RLC!B:B, E1728)} -> #N/A
A1729: интернета | B1729: 72 | C1729: 23.112392 | E1729: =MATCH(A1729, RLC!A:A, 0) -> 2960 | F1729: {=INDEX(RLC!B:B, E1729)} -> 29
A1730: когнитивных | B1730: 72 | C1730: 23.112392 | E1730: =MATCH(A1730, RLC!A:A, 0) -> #N/A | F1730: {=INDEX(RLC!B:B, E1730)} -> #N/A
... A2090: чтение | B2090: 61 | C2090: 19.581332 | E2090: =MATCH(A2090, RLC!A:A, 0) -> 2647 | F2090: {=INDEX(RLC!B:B, E2090)} -> 33
A2091: школы | B2091: 61 | C2091: 19.581332 | E2091: =MATCH(A2091, RLC!A:A, 0) -> 542 | F2091: {=INDEX(RLC!B:B, E2091)} -> 149 | G2091: =C2091>E2091 -> FALSE
A2092: больших | B2092: 60 | C2092: 19.260326 | E2092: =MATCH(A2092, RLC!A:A, 0) -> 1082 | F2092: {=INDEX(RLC!B:B, E2092)} -> 77
A2093: будем | B2093: 60 | C2093: 19.260326 | E2093: =MATCH(A2093, RLC!A:A, 0) -> 1097 | F2093: {=INDEX(RLC!B:B, E2093)} -> 76
A2094: вариативность | B2094: 60 | C2094: 19.260326 | E2094: =MATCH(A2094, RLC!A:A, 0) -> #N/A | F2094: {=INDEX(RLC!B:B, E2094)} -> #N/A
A2095: возмещения | B2095: 60 | C2095: 19.260326 | E2095: =MATCH(A2095, RLC!A:A, 0) -> #N/A | F2095: {=INDEX(RLC!B:B, E2095)} -> #N/A
A2096: возможностей | B2096: 60 | C2096: 19.260326 | E2096: =MATCH(A2096, RLC!A:A, 0) -> 2835 | F2096: {=INDEX(RLC!B:B, E2096)} -> 30
A2097: выяснить | B2097: 60 | C2097: 19.260326 | E2097: =MATCH(A2097, RLC!A:A, 0) -> 7547 | F2097: {=INDEX(RLC!B:B, E2097)} -> 10
A2098: гипотез | B2098: 60 | C2098: 19.260326 | E2098: =MATCH(A2098, RLC!A:A, 0) -> #N/A | F2098: {=INDEX(RLC!B:B, E2098)} -> #N/A
A2099: голове | B2099: 60 | C2099: 19.260326 | E2099: =MATCH(A2099, RLC!A:A, 0) -> 2131 | F2099: {=INDEX(RLC!B:B, E2099)} -> 40
A2100: гражданском | B2100: 60 | C2100: 19.260326 | E2100: =MATCH(A2100, RLC!A:A, 0) -> #N/A | F2100: {=INDEX(RLC!B:B, E2100)} -> #N/A
A2101: дается | B2101: 60 | C2101: 19.260326 | E2101: =MATCH(A2101, RLC!A:A, 0) -> 4145 | F2101: {=INDEX(RLC!B:B, E2101)} -> 20
A2102: дальнейшего | B2102: 60 | C2102: 19.260326 | E2102: =MATCH(A2102, RLC!A:A, 0) -> #N/A | F2102: {=INDEX(RLC!B:B, E2102)} -> #N/A
A2103: другая | B2103: 60 | C2103: 19.260326 | E2103: =MATCH(A2103, RLC!A:A, 0) -> 1157 | F2103: {=INDEX(RLC!B:B, E2103)} -> 73
... A2510: фоне | B2510: 50 | C2510: 16.050272 | E2510: =MATCH(A2510, RLC!A:A, 0) -> #N/A | F2510: {=INDEX(RLC!B:B, E2510)} -> #N/A
A2511: широкий | B2511: 50 | C2511: 16.050272 | E2511: =MATCH(A2511, RLC!A:A, 0) -> 6907 | F2511: {=INDEX(RLC!B:B, E2511)} -> 12 | G2511: =C2511>E2511 -> FALSE
A2512: адресован | B2512: 49 | C2512: 15.729267 | E2512: =MATCH(A2512, RLC!A:A, 0) -> #N/A | F2512: {=INDEX(RLC!B:B, E2512)} -> #N/A
A2513: база | B2513: 49 | C2513: 15.729267 | E2513: =MATCH(A2513, RLC!A:A, 0) -> #N/A | F2513: {=INDEX(RLC!B:B, E2513)} -> #N/A
A2514: вариативности | B2514: 49 | C2514: 15.729267 | E2514: =MATCH(A2514, RLC!A:A, 0) -> #N/A | F2514: {=INDEX(RLC!B:B, E2514)} -> #N/A
A2515: введения | B2515: 49 | C2515: 15.729267 | E2515: =MATCH(A2515, RLC!A:A, 0) -> 7509 | F2515: {=INDEX(RLC!B:B, E2515)} -> 10
A2516: видел | B2516: 49 | C2516: 15.729267 | E2516: =MATCH(A2516, RLC!A:A, 0) -> 1926 | F2516: {=INDEX(RLC!B:B, E2516)} -> 45
A2517: высокий | B2517: 49 | C2517: 15.729267 | E2517: =MATCH(A2517, RLC!A:A, 0) -> 2129 | F2517: {=INDEX(RLC!B:B, E2517)} -> 40
A2518: выходит | B2518: 49 | C2518: 15.729267 | E2518: =MATCH(A2518, RLC!A:A, 0) -> 3637 | F2518: {=INDEX(RLC!B:B, E2518)} -> 23
A2519: герои | B2519: 49 | C2519: 15.729267 | E2519: =MATCH(A2519, RLC!A:A, 0) -> 2502 | F2519: {=INDEX(RLC!B:B, E2519)} -> 34
A2520: глагольных | B2520: 49 | C2520: 15.729267 | E2520: =MATCH(A2520, RLC!A:A, 0) -> #N/A | F2520: {=INDEX(RLC!B:B, E2520)} -> #N/A
A2521: гпк | B2521: 49 | C2521: 15.729267 | E2521: =MATCH(A2521, RLC!A:A, 0) -> #N/A | F2521: {=INDEX(RLC!B:B, E2521)} -> #N/A
A2522: егэ | B2522: 49 | C2522: 15.729267 | E2522: =MATCH(A2522, RLC!A:A, 0) -> 3049 | F2522: {=INDEX(RLC!B:B, E2522)} -> 28
A2523: единственный | B2523: 49 | C2523: 15.729267 | E2523: =MATCH(A2523, RLC!A:A, 0) -> 1892 | F2523: {=INDEX(RLC!B:B, E2523)} -> 46
... A2664: человеке | B2664: 47 | C2664: 15.087256 | E2664: =MATCH(A2664, RLC!A:A, 0) -> 2556 | F2664: {=INDEX(RLC!B:B, E2664)} -> 34
A2665: шаг | B2665: 47 | C2665: 15.087256 | E2665: =MATCH(A2665, RLC!A:A, 0) -> 2738 | F2665: {=INDEX(RLC!B:B, E2665)} -> 32 | G2665: =C2665>E2665 -> FALSE
A2666: авторских | B2666: 46 | C2666: 14.76625 | E2666: =MATCH(A2666, RLC!A:A, 0) -> #N/A | F2666: {=INDEX(RLC!B:B, E2666)} -> #N/A
A2667: будь | B2667: 46 | C2667: 14.76625 | E2667: =MATCH(A2667, RLC!A:A, 0) -> 3245 | F2667: {=INDEX(RLC!B:B, E2667)} -> 26
A2668: бытия | B2668: 46 | C2668: 14.76625 | E2668: =MATCH(A2668, RLC!A:A, 0) -> #N/A | F2668: {=INDEX(RLC!B:B, E2668)} -> #N/A
A2669: вводит | B2669: 46 | C2669: 14.76625 | E2669: =MATCH(A2669, RLC!A:A, 0) -> #N/A | F2669: {=INDEX(RLC!B:B, E2669)} -> #N/A
A2670: вещь | B2670: 46 | C2670: 14.76625 | E2670: =MATCH(A2670, RLC!A:A, 0) -> 2655 | F2670: {=INDEX(RLC!B:B, E2670)} -> 32
A2671: взаимодействии | B2671: 46 | C2671: 14.76625 | E2671: =MATCH(A2671, RLC!A:A, 0) -> #N/A | F2671: {=INDEX(RLC!B:B, E2671)} -> #N/A
A2672: выборки | B2672: 46 | C2672: 14.76625 | E2672: =MATCH(A2672, RLC!A:A, 0) -> #N/A | F2672: {=INDEX(RLC!B:B, E2672)} -> #N/A
A2673: выделены | B2673: 46 | C2673: 14.76625 | E2673: =MATCH(A2673, RLC!A:A, 0) -> #N/A | F2673: {=INDEX(RLC!B:B, E2673)} -> #N/A
A2674: гипотезу | B2674: 46 | C2674: 14.76625 | E2674: =MATCH(A2674, RLC!A:A, 0) -> #N/A | F2674: {=INDEX(RLC!B:B, E2674)} -> #N/A
A2675: государств | B2675: 46 | C2675: 14.76625 | E2675: =MATCH(A2675, RLC!A:A, 0) -> 991 | F2675: {=INDEX(RLC!B:B, E2675)} -> 84
A2676: доме | B2676: 46 | C2676: 14.76625 | E2676: =MATCH(A2676, RLC!A:A, 0) -> 907 | F2676: {=INDEX(RLC!B:B, E2676)} -> 91
A2677: думать | B2677: 46 | C2677: 14.76625 | E2677: =MATCH(A2677, RLC!A:A, 0) -> 720 | F2677: {=INDEX(RLC!B:B, E2677)} -> 111
... A2830: ценностей | B2830: 44 | C2830: 14.124239 | E2830: =MATCH(A2830, RLC!A:A, 0) -> 1925 | F2830: {=INDEX(RLC!B:B, E2830)} -> 46
A2831: широкого | B2831: 44 | C2831: 14.124239 | E2831: =MATCH(A2831, RLC!A:A, 0) -> 5302 | F2831: {=INDEX(RLC!B:B, E2831)} -> 16 | G2831: =C2831>E2831 -> FALSE
A2832: широкой | B2832: 44 | C2832: 14.124239 | E2832: =MATCH(A2832, RLC!A:A, 0) -> 1998 | F2832: {=INDEX(RLC!B:B, E2832)} -> 44 | G2832: =C2832>E2832 -> FALSE
A2833: экономиста | B2833: 44 | C2833: 14.124239 | E2833: =MATCH(A2833, RLC!A:A, 0) -> #N/A | F2833: {=INDEX(RLC!B:B, E2833)} -> #N/A
A2834: экономического | B2834: 44 | C2834: 14.124239 | E2834: =MATCH(A2834, RLC!A:A, 0) -> 917 | F2834: {=INDEX(RLC!B:B, E2834)} -> 91
A2835: эксперта | B2835: 44 | C2835: 14.124239 | E2835: =MATCH(A2835, RLC!A:A, 0) -> #N/A | F2835: {=INDEX(RLC!B:B, E2835)} -> #N/A
A2836: января | B2836: 44 | C2836: 14.124239 | E2836: =MATCH(A2836, RLC!A:A, 0) -> 1413 | F2836: {=INDEX(RLC!B:B, E2836)} -> 61
A2837: абстрактное | B2837: 43 | C2837: 13.803234 | E2837: =MATCH(A2837, RLC!A:A, 0) -> #N/A | F2837: {=INDEX(RLC!B:B, E2837)} -> #N/A
A2838: автору | B2838: 43 | C2838: 13.803234 | E2838: =MATCH(A2838, RLC!A:A, 0) -> 6004 | F2838: {=INDEX(RLC!B:B, E2838)} -> 13
A2839: включая | B2839: 43 | C2839: 13.803234 | E2839: =MATCH(A2839, RLC!A:A, 0) -> 1415 | F2839: {=INDEX(RLC!B:B, E2839)} -> 60
A2840: встретить | B2840: 43 | C2840: 13.803234 | E2840: =MATCH(A2840, RLC!A:A, 0) -> 4555 | F2840: {=INDEX(RLC!B:B, E2840)} -> 18
A2841: выяснилось | B2841: 43 | C2841: 13.803234 | E2841: =MATCH(A2841, RLC!A:A, 0) -> 6485 | F2841: {=INDEX(RLC!B:B, E2841)} -> 12
A2842: грамматика | B2842: 43 | C2842: 13.803234 | E2842: =MATCH(A2842, RLC!A:A, 0) -> 6065 | F2842: {=INDEX(RLC!B:B, E2842)} -> 13
A2843: движений | B2843: 43 | C2843: 13.803234 | E2843: =MATCH(A2843, RLC!A:A, 0) -> 4347 | F2843: {=INDEX(RLC!B:B, E2843)} -> 19
A2844: доказывает | B2844: 43 | C2844: 13.803234 | E2844: =MATCH(A2844, RLC!A:A, 0) -> 2364 | F2844: {=INDEX(RLC!B:B, E2844)} -> 36
... A3829: чувством | B3829: 32 | C3829: 10.272174 | E3829: =MATCH(A3829, RLC!A:A, 0) -> 6906 | F3829: {=INDEX(RLC!B:B, E3829)} -> 12
...

Sheet RLC
A1: Слово | B1: Частота-RLC | C1: IPM-RLC | D1: Ранг-RLC | E1: Номер строки, на которой слово стоит в CorST
A2: и | B2: 28852 | C2: 38334.702 | E2: =MATCH(A2, CorST!A:A, 0) -> 3
A3: в | B3: 28595 | C3: 37993.234 | E3: =MATCH(A3, CorST!A:A, 0) -> 2
A4: что | B4: 12272 | C4: 16305.402 | E4: =MATCH(A4, CorST!A:A, 0) -> 7
A5: на | B5: 9984 | C5: 13265.412 | E5: =MATCH(A5, CorST!A:A, 0) -> 4
A6: не | B6: 9679 | C6: 12860.168 | E6: =MATCH(A6, CorST!A:A, 0) -> 5
A7: я | B7: 8489 | C7: 11279.055 | E7: =MATCH(A7, CorST!A:A, 0) -> 24
A8: с | B8: 6908 | C8: 9178.432 | E8: =MATCH(A8, CorST!A:A, 0) -> 6
A9: как | B9: 6227 | C9: 8273.6097 | E9: =MATCH(A9, CorST!A:A, 0) -> 8
A10: это | B10: 5389 | C10: 7160.1868 | E10: =MATCH(A10, CorST!A:A, 0) -> 15
A11: но | B11: 4307 | C11: 5722.569 | E11: =MATCH(A11, CorST!A:A, 0) -> 19
A12: он | B12: 4050 | C12: 5381.1016 | E12: =MATCH(A12, CorST!A:A, 0) -> 21
A13: о | B13: 3780 | C13: 5022.3615 | E13: =MATCH(A13, CorST!A:A, 0) -> 13
... A8127: японский | B8127: 10 | C8127: 13.286671 | E8127: =MATCH(A8127, CorST!A:A, 0) -> 14067

Sheet merge
A1: Слово | B1: IPM-CorST | C1: IPM-RLC | D1: Разница CorST - RLC
A2: а | B2: 1901.6362 | C2: 2596
A3: предлога | B3: 347.9699
A4: абзац | B4: 86.029458 | C4: 57
A5: предлогов | B5: 215.07365
A6: абзаце | B6: 43.014729 | C6: 18
A7: ст | B7: 188.7512
A8: значений | B8: 185.86215
A9: предлог | B9: 132.57525
A10: абитуриентов | B10: 3.2100544 | C10: 21
A11: напишите | C11: 182
A12: сети | B12: 106.2528
A13: абсолютно | B13: 35.631604 | C13: 61
A14: фрагмент | B14: 99.190681
A15: восприятия | B15: 94.375599
A16: судьи | B16: 92.770572
A17: судей | B17: 89.239512
A18: делу | B18: 88.918507
A19: абстрактные | B19: 8.6671469 | C19: 11
A20: колобок | B20: 80.25136
A21: ред | B21: 79.288344
A22: выделить | B22: 76.078289
A23: глагола | B23: 74.473262
A24: объекта | B24: 73.831251
A25: абсурда | B25: 9.3091578 | C25: 10
A26: озеро | C26: 173
A27: антибиотиков | C27: 156
A28: американцев | C28: 153
A29: байкал | C29: 150
A30: войне | C30: 146
A31: геополитика | C31: 134
A32: электронный | B32: 69.658181
A33: августа | B33: 25.680435 | C33: 43
A34: американцы | C34: 132
A35: синонимов | B35: 69.337175
A36: психологии | B36: 66.769132
A37: рабству | B37: 66.769132
A38: линднер | B38: 65.806115
A39: автобус | B39: 3.8520653 | C39: 11
A40: маяковского | C40: 131
A41: компенсации | B41: 62.275055
A42: доказательств | B42: 60.349023
A43: ы | B43: 59.065001
A44: употреблений | B44: 58.743996
A45: конструкций | B45: 57.459974
A46: глаголов | B46: 56.817963
A47: рекламная | B47: 56.817963
A48: специфика | B48: 55.533941
A49: судебного | B49: 55.533941
A50: инстанции | B50: 54.89193
A51: юридического | B51: 54.89193
A52: иска | B52: 53.928914
A53: автор | B53: 503.65754 | C53: 726
A54: автора | B54: 112.99392 | C54: 168
A55: дорогах | B55: 53.607909
A56: репутации | B56: 53.286903
A57: авторитет | B57: 17.334294 | C57: 18
A58: глагол | B58: 52.965898
A59: авторов | B59: 35.952609 | C59: 28
A60: автором | B60: 94.375599 | C60: 35
A61: таблица | B61: 52.644892
A62: функциональный | B62: 52.323887
A63: научная | B63: 52.002881
A64: особенностей | B64: 52.002881
A65: абзаца | B65: 51.039865
A66: хайек | B66: 50.71886
A67: пространственные | B67: 50.397854
A68: различий | B68: 50.076849
A69: судебной | B69: 49.755843
A70: автору | B70: 13.803234 | C70: 13
A71: авторы | B71: 77.683317 | C71: 84
A72: исходя | B72: 48.150816
A73: советском | C73: 130
A74: рассмотрения | B74: 47.829811
A75: семантики | B75: 47.1878
A76: лебедь | B76: 46.866794
A77: предлоги | B77: 46.866794
A78: адаптации | B78: 16.371277 | C78: 20
A79: гипотезы | B79: 46.545789
A80: адаптация | B80: 6.4201088 | C80: 11
A81: озера | C81: 127
A82: приложение | B82: 46.545789
A83: соразмерно | B83: 46.545789
A84: семантической | B84: 46.224783
A85: субъект | B85: 45.903778
A86: функций | B86: 45.903778
A87: гражданский | B87: 45.582773
A88: правке | B88: 45.261767
A89: выявить | B89: 44.619756
A90: иных | B90: 44.619756
A91: истца | B91: 44.619756
A92: кп | B92: 44.619756
A93: материалы | B93: 44.298751
... A96: абзацы | B96: 43.65674
A97: администрации | B97: 4.8150816 | C97: 10
A98: предлогом | B98: 43.335734
A99: содержания | B99: 43.335734
A100: судья | B100: 43.335734
A101: сценария | B101: 43.335734
A102: лексики | B102: 42.693724
...
